README.rst
setup.py
pytest_growl/__init__.py
pytest_growl/growl.py
pytest_growl/test_case.py
pytest_growl.egg-info/PKG-INFO
pytest_growl.egg-info/SOURCES.txt
pytest_growl.egg-info/dependency_links.txt
pytest_growl.egg-info/entry_points.txt
pytest_growl.egg-info/top_level.txt