Metadata-Version: 1.0
Name: pytest-growl
Version: 0.2
Summary: Growl notifications for pytest results.
Home-page: UNKNOWN
Author: Anthony Long
Author-email: antlong@gmail.com
License: UNKNOWN
Keywords: pytest,pytest-,growl,py.test
Platform: UNKNOWN
